.gitignore
.pre-commit-config.yaml
.pylintrc
README.rst
setup.py
subpop.yaml
xidle.c
.idea/.gitignore
.idea/funtoo-powerbus.iml
.idea/misc.xml
.idea/modules.xml
.idea/vcs.xml
.idea/codeStyles/codeStyleConfig.xml
.idea/inspectionProfiles/profiles_settings.xml
bin/funtoo-idled
bin/funtoo-powerbus
bin/powerstatus
docs/idle-sleep-spec.rst
funtoo_powerbus.egg-info/PKG-INFO
funtoo_powerbus.egg-info/SOURCES.txt
funtoo_powerbus.egg-info/dependency_links.txt
funtoo_powerbus.egg-info/requires.txt
funtoo_powerbus.egg-info/top_level.txt
old/websocket-stuff.py
old/websocket.py
plugins/init.py
plugins/session.py
plugins/socket.py
plugins/system.py
powerbus/__init__.py