Metadata-Version: 2.1
Name: funtoo-powerbus
Version: 0.2.9
Summary: Funtoo Power Management Framework
Home-page: https://code.funtoo.org/bitbucket/users/drobbins/repos/funtoo-powerbus/browse
Author: Daniel Robbins
Author-email: drobbins@funtoo.org
License: UNKNOWN
Platform: UNKNOWN
Classifier: Programming Language :: Python :: 3
Classifier: License :: OSI Approved :: Apache Software License
Classifier: Operating System :: POSIX :: Linux
Requires-Python: >=3.7
